Workbook
Name A_08: '[1]Monthly Return Data Input'!$D$2:$D$79
Name A_08: 'Monthly Return Data Input'!$D$2:$D$79
Name A_4A: 'Monthly Return Data Input'!$D$53:$D$287
Name A_60: '[1]Monthly Return Data Input'!$D$227:$D$287
Name A_60: 'Monthly Return Data Input'!$D$227:$D$287
Name A_comm: '[1]Monthly Return Data Input'!$D$53:$D$287
Name A_comm: 'Monthly Return Data Input'!$D$53:$D$287
Name A_ret: '[1]Monthly Return Data Input'!$D$2:$D$287
Name A_ret: 'Monthly Return Data Input'!$D$2:$D$287
Name GSPC_08: '[1]Monthly Return Data Input'!$B$2:$B$79
Name GSPC_08: 'Monthly Return Data Input'!$B$2:$B$79
Name GSPC_60: '[1]Monthly Return Data Input'!$B$227:$B$287
Name GSPC_60: 'Monthly Return Data Input'!$B$227:$B$287
Name GSPC_comm: '[1]Monthly Return Data Input'!$B$53:$B$287
Name GSPC_comm: 'Monthly Return Data Input'!$B$53:$B$287
Name GSPC_ret: '[1]Monthly Return Data Input'!$B$2:$B$287
Name GSPC_ret: 'Monthly Return Data Input'!$B$2:$B$287
Name MMM_08: '[1]Monthly Return Data Input'!$C$2:$C$79
Name MMM_08: 'Monthly Return Data Input'!$C$2:$C$79
Name MMM_4A: 'Monthly Return Data Input'!$C$53:$C$287
Name MMM_60: '[1]Monthly Return Data Input'!$C$227:$C$287
Name MMM_60: 'Monthly Return Data Input'!$C$227:$C$287
Name MMM_comm: '[1]Monthly Return Data Input'!$C$53:$C$287
Name MMM_comm: 'Monthly Return Data Input'!$C$53:$C$287
Name MMM_ret: '[1]Monthly Return Data Input'!$C$2:$C$287
Name MMM_ret: 'Monthly Return Data Input'!$C$2:$C$287
Name SLV_4A: 'Monthly Return Data Input'!$E$53:$E$287
Name SLV_60: '[1]Monthly Return Data Input'!$E$227:$E$287
Name SLV_60: 'Monthly Return Data Input'!$E$227:$E$287
Name SLV_comm: '[1]Monthly Return Data Input'!$E$53:$E$287
Name SLV_comm: 'Monthly Return Data Input'!$E$53:$E$287
Name SLV_ret: '[1]Monthly Return Data Input'!$E$2:$E$287
Name SLV_ret: 'Monthly Return Data Input'!$E$2:$E$287
Name SPY_4A: 'Monthly Return Data Input'!$B$53:$B$287

Sheet Security Descriptions
A1: Group Members:Ethan Nguyen, Ethan Paduch, Elandrous Peoples, Eli Jordan, Will Xu
A2: SECURITY | B2: SPY | C2: A | D2: MMM | E2: SLV
A3: ISSUER | B3: State Street Global Advisors | C3: Agilent Technologies, Inc. | D3: 3M Company | E3: BlackRock
A4: FIRST ISSUED/OFFER DATE | B4: 33991 | C4: 36482 | D4: 16816 | E4: 38835
A5: PURPOSE | B5: ETF that tracks the S&P 500 Index, providing a well-diversified, market-cap-weighted portfolio of 500 of the largest U.S. stocks for broad market exposure. | C5: Stock of a company providing tools to analyze structural properties of chemicals, molecules, and cells, with applications in life sciences, diagnostics, and applied markets; operates in segments like life sciences/applied tools, cross-lab consumables/services, and diagnostics/genomics. | D5: Stock of a multinational conglomerate offering diversified technology products and services in safety/industrial (e.g., abrasives, respiratory protection), transportation/electronics (e.g., films, data center solutions), and consumer segments (e.g., cleaning products, office supplies); founded in 1902 and recently spun off its healthcare business. | E5: ETF that seeks to reflect the performance of the price of silver bullion, holding physical silver without active management to provide commodity exposure.
A6: EXPENSE RATIO | B6: =0.09% -> 0.0009 | C6: N/A (stock) | D6: N/A (stock) | E6: =0.5% -> 0.005
A7: TURNOVER RATIO | B7: =2% -> 0.02 | C7: N/A (stock) | D7: N/A (stock) | E7: =23% -> 0.23
A8: MORNINGSTAR STYLE BOX | B8: Large blend | C8: N/A (sStock) | D8: N/A (stock) | E8: Commodities / Precious Metals
A9: COMPETITOR ETF/RIVAL FIRM | B9: Vanguard S&P 500 ETF (VOO) | C9: Thermo Fisher Scientific (TMO) | D9: Honeywell International (HON) | E9: Aberdeen Standard Physical Silver ETF (SIVR)
A10: DIVIDEND YIELD | B10: =1.3% -> 0.013 | C10: 0.007 | D10: 0.06 | E10: 0
A11: INDUSTRY/SECTOR | B11: Broad Market U.S. Equities (ETF) | C11: Life Sciences Tools & Diagnostics | D11: Industrials / Diversified Manufacturing | E11: Commodity ETF – Precious Metals

Sheet Monthly Return Data Input
A1: Date | B1: SPY_ret | C1: MMM_ret | D1: A_ret | E1: SLV_ret
A2: 37288 | B2: -0.020766211 | C2: 0.06243228 | D2: 0.026359439 | E2: -
A3: 37316 | B3: 0.036738893 | C3: -0.0194272 | D3: 0.12231207 | E3: -
A4: 37347 | B4: -0.061417626 | C4: 0.093818149 | D4: -0.14044631 | E4: -
A5: 37377 | B5: -0.0090814814 | C5: -0.0029413561 | D5: -0.12246298 | E5: -
A6: 37408 | B6: -0.072455354 | C6: -0.014561737 | D6: -0.10314744 | E6: -
A7: 37438 | B7: -0.079004275 | C7: 0.023007962 | D7: -0.2016912 | E7: -
A8: 37469 | B8: 0.0048814333 | C8: -0.0069933442 | D8: -0.28866542 | E8: -
A9: 37500 | B9: -0.11002432 | C9: -0.11563369 | D9: -0.027550228 | E9: -
A10: 37530 | B10: 0.0864488 | C10: 0.15431391 | D10: 0.05283309 | E10: -
A11: 37561 | B11: 0.057069621 | C11: 0.022924838 | D11: 0.41163637 | E11: -
A12: 37591 | B12: -0.060332572 | C12: -0.045821857 | D12: -0.074703708 | E12: -
A13: 37622 | B13: -0.027414693 | C13: 0.010138367 | D13: -0.082405594 | E13: -
... A52: 38808 | B52: 0.012155653 | C52: 0.12868339 | D52: 0.023169267 | E52: -
A53: 38838 | B53: -0.030916917 | C53: -0.020718906 | D53: -0.091879086 | E53: -0.085722559
A54: 38869 | B54: 8.6596505e-05 | C54: -0.02939832 | D54: -0.095442858 | E54: -0.1179126
A55: 38899 | B55: 0.0050858788 | C55: -0.12838981 | D55: -0.098859134 | E55: 0.02477781
A56: 38930 | B56: 0.021274193 | C56: 0.018466343 | D56: 0.13080169 | E56: 0.13079282
A57: 38961 | B57: 0.024566298 | C57: 0.044676423 | D57: 0.016479794 | E57: -0.11287572
A58: 38991 | B58: 0.031508004 | C58: 0.059393103 | D58: 0.089018246 | E58: 0.07134743
A59: 39022 | B59: 0.016466656 | C59: 0.033231664 | D59: -0.1056182 | E59: 0.13857196
A60: 39052 | B60: 0.012615783 | C60: -0.037895913 | D60: 0.161657 | E60: -0.079037805
A61: 39083 | B61: 0.014059043 | C61: -0.046580762 | D61: -0.081778924 | E61: 0.050684037
A62: 39114 | B62: -0.021846176 | C62: -0.0029607125 | D62: -0.007813018 | E62: 0.045057725
A63: 39142 | B63: 0.0099799829 | C63: 0.038230334 | D63: 0.06110285 | E63: -0.054725647
A64: 39173 | B64: 0.04329069 | C64: 0.08295106 | D64: 0.020183778 | E64: -0.0012732323
... A287: 45962 | B287: -0.0064194256 | C287: -0.013093049 | D287: 0.0028013368 | E287: -0.0081798866

Sheet Summary Statistics
C2: Arithmetic Mean | D2: Geometric Mean | E2: Variance | F2: Correlation | G2: St. Dev. | H2: Alpha | I2: Beta
B3: A | C3: =SUM(A_ret)/COUNT(A_ret) -> 0.011785257 | D3: {=(PRODUCT(1+A_60))^(1/COUNT(A_60))-1} -> 0.006558974 | E3: =VAR(A_ret) -> 0.0090135826 | F3: =CORREL(A_ret,GSPC_ret) -> 0.63746986 | G3: =_xlfn.STDEV.S(A_ret) -> 0.094939889
B4: A-60M | C4: =SUM(A_60)/COUNT(A_60) -> 0.009807631 | D4: {=(PRODUCT(1+A_60))^(1/COUNT(A_60))-1} -> 0.006558974 | E4: =VAR(A_60) -> 0.006707039 | G4: =_xlfn.STDEV.S(A_60) -> 0.081896514 | H4: =INTERCEPT(A_60,GSPC_60) -> -0.0070882186 | I4: =SLOPE(A_60,GSPC_60) -> 1.2932843
B5: GSPC | C5: =SUM(GSPC_ret)/COUNT(GSPC_ret) -> 0.0072239439 | D5: {=(PRODUCT(1+GSPC_60))^(1/COUNT(GSPC_60))-1} -> 0.012065638 | E5: =VAR(GSPC_ret) -> 0.0018458189 | F5: =CORREL(GSPC_ret,GSPC_ret) -> 1 | G5: =_xlfn.STDEV.S(GSPC_ret) -> 0.042962994
B6: GSPC-60M | C6: =SUM(GSPC_60)/COUNT(GSPC_60) -> 0.013064296 | D6: {=(PRODUCT(1+GSPC_60))^(1/COUNT(GSPC_60))-1} -> 0.012065638 | E6: =VAR(GSPC_60) -> 0.0020287318 | G6: =_xlfn.STDEV.S(GSPC_60) -> 0.045041445 | H6: =INTERCEPT(GSPC_60,GSPC_60) -> 0 | I6: =SLOPE(GSPC_60,GSPC_60) -> 1
B7: MMM | C7: =SUM(MMM_ret)/COUNT(MMM_ret) -> 0.0086779335 | D7: {=(PRODUCT(1+MMM_60))^(1/COUNT(MMM_60))-1} -> 0.0064873867 | E7: =VAR(MMM_ret) -> 0.0038692704 | F7: =CORREL(MMM_ret,GSPC_ret) -> 0.61430069 | G7: =_xlfn.STDEV.S(MMM_ret) -> 0.06220346
B8: MMM-60M | C8: =SUM(MMM_60)/COUNT(MMM_60) -> 0.0095382101 | D8: {=(PRODUCT(1+MMM_60))^(1/COUNT(MMM_60))-1} -> 0.0064873867 | E8: =VAR(MMM_60) -> 0.0063556501 | G8: =_xlfn.STDEV.S(MMM_60) -> 0.079722331 | H8: =INTERCEPT(MMM_60,GSPC_60) -> -0.0040239608 | I8: =SLOPE(MMM_60,GSPC_60) -> 1.0381096
B9: SLV | C9: =AVERAGE(SLV_ret) -> 0.0089298086 | D9: {=(PRODUCT(1+SLV_60))^(1/COUNT(SLV_60))-1} -> 0.011303 | E9: =VAR(SLV_ret) -> 0.0081768641 | F9: =CORREL(SLV_ret,GSPC_ret) -> 0.26487429 | G9: =_xlfn.STDEV.S(SLV_ret) -> 0.090426014
B10: SLV-60M | C10: =AVERAGE(SLV_60) -> 0.013874332 | D10: {=(PRODUCT(1+SLV_60))^(1/COUNT(SLV_60))-1} -> 0.011303 | E10: =VAR(SLV_60) -> 0.0053701135 | G10: =_xlfn.STDEV.S(SLV_60) -> 0.073281059 | H10: =INTERCEPT(SLV_60,GSPC_60) -> 0.0087572016 | I10: =SLOPE(SLV_60,GSPC_60) -> 0.39168817
A13: Correlation Matrix
C14: GSPC | D14: A | E14: MMM | F14: SLV
B15: GSPC | C15: =CORREL(GSPC_comm,GSPC_comm) -> 1 | D15: =CORREL(GSPC_comm,A_comm) -> 0.68014066 | E15: =CORREL(GSPC_comm,MMM_comm) -> 0.65863401 | F15: =CORREL(GSPC_comm,SLV_comm) -> 0.26487429
B16: A | C16: =CORREL(A_comm,GSPC_comm) -> 0.68014066 | D16: =CORREL(A_comm,A_comm) -> 1 | E16: =CORREL(A_comm,MMM_comm) -> 0.61400623 | F16: =CORREL(A_comm,SLV_comm) -> 0.21918148
B17: MMM | C17: =CORREL(MMM_comm,GSPC_comm) -> 0.65863401 | D17: =CORREL(MMM_comm,A_comm) -> 0.61400623 | E17: =CORREL(MMM_comm,MMM_comm) -> 1 | F17: =CORREL(MMM_comm,SLV_comm) -> 0.1393616
B18: SLV | C18: =CORREL(SLV_comm,GSPC_comm) -> 0.26487429 | D18: =CORREL(SLV_comm,A_comm) -> 0.21918148 | E18: =CORREL(SLV_comm,MMM_comm) -> 0.1393616 | F18: =CORREL(SLV_comm,SLV_comm) -> 1

Sheet Markowitz Model
D2: Arith Mean | E2: Geo Mean | F2: Standard Deviation | H2: Arithmetic Mean
C3: SPY | D3: =AVERAGE(GSPC_08) -> 0.0021141665 | E3: {=(PRODUCT(1+GSPC_08))^(1/COUNT(GSPC_08))-1} -> 0.0014697613 | F3: =_xlfn.STDEV.S(GSPC_08) -> 0.035886861 | H3: Rf | I3: w_SPY | J3: w_A | K3: w_MMM | M3: St. Dev. | N3: E[R] | O3: Sharpe
C4: MMM | D4: =AVERAGE(MMM_08) -> 0.0062803018 | E4: {=PRODUCT(1+MMM_08)^(1/COUNT(MMM_08))-1} -> 0.0048361221 | F4: =_xlfn.STDEV.S(MMM_08) -> 0.054194946 | H4: =1%/12 -> 0.00083333333 | I4: 0 | J4: 0.76392465 | K4: 0.23607535 | L4: =SUM(I4:K4) -> 1 | M4: =SQRT(SUM(D28:F30)) -> 0.053306596 | N4: =D3*I4+D4*J4+D5*K4 -> 0.0071202263 | O4: =(N4-H4)/M4 -> 0.11793837
C5: A | D5: =AVERAGE(A_08) -> 0.0098381682 | E5: {=PRODUCT(1+A_08)^(1/COUNT(A_08))-1} -> 0.0029775762 | F5: =_xlfn.STDEV.S(A_08) -> 0.11936989
H7: Geometric Mean
H8: Rf | I8: w_SPY | J8: w_A | K8: w_MMM | M8: St. Dev. | N8: E[R] | O8: Sharpe
H9: =1%/12 -> 0.00083333333 | I9: 0 | J9: 1 | K9: 0 | L9: =SUM(I9:K9) -> 1 | M9: =SQRT(SUM(D36:F38)) -> 0.053622616 | N9: =I9*E3+J9*E4+K9*E5 -> 0.0048361221 | O9: =(N9-H9)/M9 -> 0.074647398
B10: Correlation Matrix
D11: SPY | E11: A | F11: MMM
C12: SPY | D12: =CORREL(GSPC_08,GSPC_08) -> 1 | E12: =CORREL(GSPC_08,A_08) -> 0.54122945 | F12: =CORREL(GSPC_08,MMM_08) -> 0.39690826 | H12: Solver Portfolio-Weight Optimization
C13: A | D13: =CORREL(A_08,GSPC_08) -> 0.54122945 | E13: =CORREL(A_08,A_08) -> 1 | F13: =CORREL(A_08,MMM_08) -> 0.14289758 | H13: Rf | I13: W_SPY | J13: W_A | K13: w_MMM | M13: St.Dev | N13: E[R] | O13: Sharpe
C14: MMM | D14: =CORREL(MMM_08,GSPC_08) -> 0.39690826 | E14: =CORREL(MMM_08,A_08) -> 0.14289758 | F14: =CORREL(MMM_08,MMM_08) -> 1 | H14: 0.0008 | I14: =0 -> 0 | J14: 0.94111784 | K14: 0.0588315 | L14: =SUM(I14:K14) -> 0.99994934 | M14: {=SQRT(MMULT(MMULT(I14:K14,$D$20:$F$22),TRANSPOSE(I14:K14)))} -> 0.05246977 | N14: =I14*$D$3 + K14*$D$4 + J14*$D$5 -> 0.0096283552 | O14: =(N14-H14)/M14 -> 0.16825603
B17: Bordered Cov. Matrix
D19: SPY | E19: A | F19: MMM
C20: SPY | D20: =$H20*H20*D12 -> 0.0012878668 | E20: =H20*I$20*E12 -> 0.0010526298 | F20: =H20*J$20*F12 -> 0.0017002798 | H20: =_xlfn.STDEV.S(GSPC_08) -> 0.035886861 | I20: =F4 -> 0.054194946 | J20: =F5 -> 0.11936989
C21: A | D21: =H$20*H21*D13 -> 0.0010526298 | E21: =H21*I$20*E13 -> 0.0029370921 | F21: =H21*J$20*F13 -> 0.00092443935 | H21: =_xlfn.STDEV.S(MMM_08) -> 0.054194946
C22: MMM | D22: =H$20*H22*D14 -> 0.0017002798 | E22: =H22*I$20*E14 -> 0.00092443935 | F22: =H22*J$20*F14 -> 0.014249169 | H22: =_xlfn.STDEV.S(A_08) -> 0.11936989
B25: Border Mult Cov. Matrix Arithmetic
D26: =I4 -> 0 | E26: =J4 -> 0.76392465 | F26: =K4 -> 0.23607535
D27: SPY | E27: A | F27: MMM
B28: =I4 -> 0 | C28: SPY | D28: =D20*D$26*$B28 -> 0 | E28: =E20*E$26*$B28 -> 0 | F28: =F20*F$26*$B28 -> 0
B29: =J4 -> 0.76392465 | C29: A | D29: =D21*D$26*$B29 -> 0 | E29: =E21*E$26*$B29 -> 0.0017140308 | F29: =F21*F$26*$B29 -> 0.00016671688
B30: =K4 -> 0.23607535 | C30: MMM | D30: =D22*D$26*$B30 -> 0 | E30: =E22*E$26*$B30 -> 0.00016671688 | F30: =F22*F$26*$B30 -> 0.0007941286
B33: Border Mult Cov. Matrix Geometric
D34: =I9 -> 0 | E34: =J9 -> 1 | F34: =K9 -> 0
D35: SPY | E35: A | F35: MMM
B36: =I9 -> 0 | C36: SPY | D36: 0.00014281026 | E36: 0.00011672507 | F36: 0.00018910852
B37: =J9 -> 1 | C37: A | D37: 0.00011672507 | E37: 0.00032569121 | F37: 0.00010281799
B38: =K9 -> 0 | C38: MMM | D38: 0.00018910852 | E38: 0.00010281799 | F38: 0.0015895803

Sheet Optimal Ports
B2: Date | C2: SPY | D2: A | E2: MMM | F2: m_port_arith | G2: m_port_geom | H2: French RF | I2: RF | J2: excess_arith | K2: excess_geom | M2: Model | N2: Sharpe
B3: 39661 | C3: -0.020766211 | D3: -0.036051347 | E3: 0.017190543 | F3: ='Markowitz Model'!$I$4*C3+'Markowitz Model'!$J$4*D3+'Markowitz Model'!$K$4*E3 -> -0.023482249 | G3: ='Markowitz Model'!$I$9*C3+'Markowitz Model'!$J$9*D3+'Markowitz Model'!$K$9*E3 -> -0.036051347 | H3: 0.13 | I3: =H3/100 -> 0.0013 | J3: =F3-I3 -> -0.024782249 | K3: =G3-I3 -> -0.037351347 | M3: Arithmetic | N3: =AVERAGE(J3:J210)/_xlfn.STDEV.S(K3:K210) -> 0.1278956
B4: 39692 | C4: 0.036738893 | D4: -0.14672058 | E4: -0.039213337 | F4: ='Markowitz Model'!$I$4*C4+'Markowitz Model'!$J$4*D4+'Markowitz Model'!$K$4*E4 -> -0.12134077 | G4: ='Markowitz Model'!$I$9*C4+'Markowitz Model'!$J$9*D4+'Markowitz Model'!$K$9*E4 -> -0.14672058 | H4: 0.15 | I4: =H4/100 -> 0.0015 | J4: =F4-I4 -> -0.12284077 | K4: =G4-I4 -> -0.14822058 | M4: Geometric | N4: =AVERAGE(K3:K210)/_xlfn.STDEV.S(K3:K210) -> 0.13611514
B5: 39722 | C5: -0.061417626 | D5: -0.25185436 | E5: -0.058703048 | F5: ='Markowitz Model'!$I$4*C5+'Markowitz Model'!$J$4*D5+'Markowitz Model'!$K$4*E5 -> -0.2062561 | G5: ='Markowitz Model'!$I$9*C5+'Markowitz Model'!$J$9*D5+'Markowitz Model'!$K$9*E5 -> -0.25185436 | H5: 0.08 | I5: =H5/100 -> 0.0008 | J5: =F5-I5 -> -0.2070561 | K5: =G5-I5 -> -0.25265436
B6: 39753 | C6: -0.0090814814 | D6: -0.15141901 | E6: 0.040902241 | F6: ='Markowitz Model'!$I$4*C6+'Markowitz Model'!$J$4*D6+'Markowitz Model'!$K$4*E6 -> -0.10601671 | G6: ='Markowitz Model'!$I$9*C6+'Markowitz Model'!$J$9*D6+'Markowitz Model'!$K$9*E6 -> -0.15141901 | H6: 0.03 | I6: =H6/100 -> 0.0003 | J6: =F6-I6 -> -0.10631671 | K6: =G6-I6 -> -0.15171901
B7: 39783 | C7: -0.072455354 | D7: -0.16994179 | E7: -0.13332564 | F7: ='Markowitz Model'!$I$4*C7+'Markowitz Model'!$J$4*D7+'Markowitz Model'!$K$4*E7 -> -0.16129762 | G7: ='Markowitz Model'!$I$9*C7+'Markowitz Model'!$J$9*D7+'Markowitz Model'!$K$9*E7 -> -0.16994179 | H7: 0 | I7: =H7/100 -> 0 | J7: =F7-I7 -> -0.16129762 | K7: =G7-I7 -> -0.16994179
B8: 39814 | C8: -0.079004275 | D8: 0.15674974 | E8: -0.06517243 | F8: ='Markowitz Model'!$I$4*C8+'Markowitz Model'!$J$4*D8+'Markowitz Model'!$K$4*E8 -> 0.10435938 | G8: ='Markowitz Model'!$I$9*C8+'Markowitz Model'!$J$9*D8+'Markowitz Model'!$K$9*E8 -> 0.15674974 | H8: 0 | I8: =H8/100 -> 0 | J8: =F8-I8 -> 0.10435938 | K8: =G8-I8 -> 0.15674974
B9: 39845 | C9: 0.0048814333 | D9: -0.23285379 | E9: -0.15486115 | F9: ='Markowitz Model'!$I$4*C9+'Markowitz Model'!$J$4*D9+'Markowitz Model'!$K$4*E9 -> -0.21444165 | G9: ='Markowitz Model'!$I$9*C9+'Markowitz Model'!$J$9*D9+'Markowitz Model'!$K$9*E9 -> -0.23285379 | H9: 0.01 | I9: =H9/100 -> 0.0001 | J9: =F9-I9 -> -0.21454165 | K9: =G9-I9 -> -0.23295379
B10: 39873 | C10: -0.11002432 | D10: 0.1081471 | E10: 0.10559952 | F10: ='Markowitz Model'!$I$4*C10+'Markowitz Model'!$J$4*D10+'Markowitz Model'!$K$4*E10 -> 0.10754568 | G10: ='Markowitz Model'!$I$9*C10+'Markowitz Model'!$J$9*D10+'Markowitz Model'!$K$9*E10 -> 0.1081471 | H10: 0.02 | I10: =H10/100 -> 0.0002 | J10: =F10-I10 -> 0.10734568 | K10: =G10-I10 -> 0.1079471
B11: 39904 | C11: 0.0864488 | D11: 0.18802833 | E11: 0.15848737 | F11: ='Markowitz Model'!$I$4*C11+'Markowitz Model'!$J$4*D11+'Markowitz Model'!$K$4*E11 -> 0.18105444 | G11: ='Markowitz Model'!$I$9*C11+'Markowitz Model'!$J$9*D11+'Markowitz Model'!$K$9*E11 -> 0.18802833 | H11: 0.01 | I11: =H11/100 -> 0.0001 | J11: =F11-I11 -> 0.18095444 | K11: =G11-I11 -> 0.18792833
B12: 39934 | C12: 0.057069621 | D12: -0.0016428013 | E12: -0.0086807094 | F12: ='Markowitz Model'!$I$4*C12+'Markowitz Model'!$J$4*D12+'Markowitz Model'!$K$4*E12 -> -0.0033042779 | G12: ='Markowitz Model'!$I$9*C12+'Markowitz Model'!$J$9*D12+'Markowitz Model'!$K$9*E12 -> -0.0016428013 | H12: 0 | I12: =H12/100 -> 0 | J12: =F12-I12 -> -0.0033042779 | K12: =G12-I12 -> -0.0016428013
B13: 39965 | C13: -0.060332572 | D13: 0.11409742 | E13: 0.06171739 | F13: ='Markowitz Model'!$I$4*C13+'Markowitz Model'!$J$4*D13+'Markowitz Model'!$K$4*E13 -> 0.10173179 | G13: ='Markowitz Model'!$I$9*C13+'Markowitz Model'!$J$9*D13+'Markowitz Model'!$K$9*E13 -> 0.11409742 | H13: 0.01 | I13: =H13/100 -> 0.0001 | J13: =F13-I13 -> 0.10163179 | K13: =G13-I13 -> 0.11399742
B14: 39995 | C14: -0.027414693 | D14: 0.14327938 | E14: 0.17337756 | F14: ='Markowitz Model'!$I$4*C14+'Markowitz Model'!$J$4*D14+'Markowitz Model'!$K$4*E14 -> 0.15038482 | G14: ='Markowitz Model'!$I$9*C14+'Markowitz Model'!$J$9*D14+'Markowitz Model'!$K$9*E14 -> 0.14327938 | H14: 0.01 | I14: =H14/100 -> 0.0001 | J14: =F14-I14 -> 0.15028482 | K14: =G14-I14 -> 0.14317938
B15: 40026 | C15: -0.017003608 | D15: 0.10594283 | E15: 0.022404779 | F15: ='Markowitz Model'!$I$4*C15+'Markowitz Model'!$J$4*D15+'Markowitz Model'!$K$4*E15 -> 0.086221554 | G15: ='Markowitz Model'!$I$9*C15+'Markowitz Model'!$J$9*D15+'Markowitz Model'!$K$9*E15 -> 0.10594283 | H15: 0.01 | I15: =H15/100 -> 0.0001 | J15: =F15-I15 -> 0.086121554 | K15: =G15-I15 -> 0.10584283
B16: 40057 | C16: 0.0083575677 | D16: 0.083723245 | E16: 0.031052976 | F16: ='Markowitz Model'!$I$4*C16+'Markowitz Model'!$J$4*D16+'Markowitz Model'!$K$4*E16 -> 0.071289093 | G16: ='Markowitz Model'!$I$9*C16+'Markowitz Model'!$J$9*D16+'Markowitz Model'!$K$9*E16 -> 0.083723245 | H16: 0.01 | I16: =H16/100 -> 0.0001 | J16: =F16-I16 -> 0.071189093 | K16: =G16-I16 -> 0.083623245
... B210: 45962 | C210: -0.065777731 | D210: 0.0028013368 | E210: -0.013093049 | F210: ='Markowitz Model'!$I$4*C210+'Markowitz Model'!$J$4*D210+'Markowitz Model'!$K$4*E210 -> -0.00095093588 | G210: ='Markowitz Model'!$I$9*C210+'Markowitz Model'!$J$9*D210+'Markowitz Model'!$K$9*E210 -> 0.0028013368 | H210: 0.4 | I210: =H210/100 -> 0.004 | J210: =F210-I210 -> -0.0049509359 | K210: =G210-I210 -> -0.0011986632

Sheet Markowitz II
C2: Arith Mean | D2: Geo Mean | E2: Standard Deviation | H2: Arithmetic
B3: SPY | C3: =AVERAGE(SPY_4A) -> 0.0080059016 | D3: {=(PRODUCT(1+SPY_4A))^(1/COUNT(SPY_4A))-1} -> 0.0070283463 | E3: =_xlfn.STDEV.S(SPY_4A) -> 0.044020337 | H3: Rf | I3: W_SPY | J3: W_A | K3: W_MMM | L3: W_SLV
B4: A | C4: =AVERAGE(A_4A) -> 0.011451661 | D4: {=(PRODUCT(1+A_4A))^(1/COUNT(A_4A))-1} -> 0.0079168028 | E4: =_xlfn.STDEV.S(A_4A) -> 0.084360679 | H4: =1%/12 -> 0.00083333333 | I4: 0.76365492 | J4: 0.068311354 | K4: 0.027609596 | L4: 0.14042413 | M4: =SUM(I4:L4) -> 1
B5: MMM | C5: =AVERAGE(MMM_4A) -> 0.0080216585 | D5: {=(PRODUCT(1+MMM_4A))^(1/COUNT(MMM_4A))-1} -> 0.006018652 | E5: =_xlfn.STDEV.S(MMM_4A) -> 0.06353194
B6: SLV | C6: =AVERAGE(SLV_4A) -> 0.0089298086 | D6: {=(PRODUCT(1+SLV_4A))^(1/COUNT(SLV_4A))-1} -> 0.0049084562 | E6: =_xlfn.STDEV.S(SLV_4A) -> 0.090426014 | J6: St. Dev | K6: E[r] | L6: Sharpe
J7: =SQRT(SUM(C25:F28)) -> 0.044109018 | K7: =I4*C3+J4*C4+K4*C5+L4*C6 -> 0.00837146 | L7: =(K7-H4)/J7 -> 0.17089763
A9: Cov. Matrix | C9: SPY | D9: A | E9: MMM | F9: SLV | H9: Geometric
B10: SPY | C10: =CORREL(SPY_4A,SPY_4A) -> 1 | D10: =CORREL(A_4A,SPY_4A) -> 0.68014066 | E10: =CORREL(SPY_4A,MMM_4A) -> 0.65863401 | F10: =CORREL(SPY_4A,SLV_4A) -> 0.26487429 | H10: Rf | I10: W_SPY | J10: W_A | K10: W_MMM | L10: W_SLV
B11: A | C11: =CORREL(A_4A,SPY_4A) -> 0.68014066 | D11: 1 | E11: =CORREL(A_4A,MMM_4A) -> 0.61400623 | F11: =CORREL(A_4A,SLV_4A) -> 0.21918148 | H11: =1%/12 -> 0.00083333333 | I11: 0.97139826 | J11: 0 | K11: 0 | L11: 0.02860174 | M11: =SUM(I11:L11) -> 1
B12: MMM | C12: =CORREL(MMM_4A,SPY_4A) -> 0.65863401 | D12: =CORREL(A_4A,MMM_4A) -> 0.61400623 | E12: 1 | F12: =CORREL(MMM_4A,SLV_4A) -> 0.1393616
B13: SLV | C13: =CORREL(SLV_4A,SPY_4A) -> 0.26487429 | D13: =CORREL(SLV_4A,A_4A) -> 0.21918148 | E13: =CORREL(SLV_4A,MMM_4A) -> 0.1393616 | F13: 1 | J13: St.Dev | K13: E[r] | L13: Sharpe
J14: =SQRT(SUM(C34:F37)) -> 0.043517856 | K14: =I11*D3+J11*D4+K11*D5+L11*D6 -> 0.0069677138 | L14: =(K14-H11)/J14 -> 0.14096238
C15: =E3 -> 0.044020337 | D15: =E4 -> 0.084360679 | E15: =E5 -> 0.06353194 | F15: =E6 -> 0.090426014
A16: Bordered Cov Matrix | C16: SPY | D16: A | E16: MMM | F16: SLV
B17: SPY | C17: =C10*C$15*$A18 -> 0.00193779 | D17: =D10*D$15*$A18 -> 0.0025257605 | E17: =E10*E$15*$A18 -> 0.001842 | F17: =F10*F$15*$A18 -> 0.0010543543 | H17: Three Asset Arithmetic
A18: =E3 -> 0.044020337 | B18: A | C18: =C11*C$15*$A19 -> 0.0025257605 | D18: =D11*D$15*$A19 -> 0.0071167242 | E18: =E11*E$15*$A19 -> 0.0032908263 | F18: =F11*F$15*$A19 -> 0.001672004 | H18: Rf | I18: W_SPY | J18: W_A | K18: W_MMM
A19: =E4 -> 0.084360679 | B19: MMM | C19: =C12*C$15*$A20 -> 0.001842 | D19: =D12*D$15*$A20 -> 0.0032908263 | E19: =E12*E$15*$A20 -> 0.0040363074 | F19: =F12*F$15*$A20 -> 0.00080062404 | H19: =1%/12 -> 0.00083333333 | I19: 0.90025659 | J19: 0.08974319 | K19: 0.010000238 | L19: =SUM(I19:K19) -> 1
A20: =E5 -> 0.06353194 | B20: SLV | C20: =C13*C$15*$A21 -> 0.0010543543 | D20: =D13*D$15*$A21 -> 0.001672004 | E20: =E13*E$15*$A21 -> 0.00080062404 | F20: =F13*F$15*$A21 -> 0.0081768641
A21: =E6 -> 0.090426014 | J21: St.Dev | K21: E[r] | L21: Sharpe
J22: =SQRT(SUM(C43:E45)) -> 0.045556784 | K22: =I19*C3+J19*C4+K19*C5 -> 0.0083152928 | L22: =(K22-H19)/J22 -> 0.16423371
A23: Border Mult Cov Matrix Arithmetic Four Asset | C23: =I4 -> 0.76365492 | D23: =J4 -> 0.068311354 | E23: =K4 -> 0.027609596 | F23: =L4 -> 0.14042413
C24: SPY | D24: A | E24: MMM | F24: SLV
B25: SPY | C25: =C17*C$23*$A26 -> 0.0011300588 | D25: =D17*D$23*$A26 -> 0.00013175958 | E25: =E17*E$23*$A26 -> 3.8837103e-05 | F25: =F17*F$23*$A26 -> 0.00011306429
A26: =I4 -> 0.76365492 | B26: A | C26: =C18*C$23*$A27 -> 0.00013175958 | D26: =D18*D$23*$A27 -> 3.3209774e-05 | E26: =E18*E$23*$A27 -> 6.2066593e-06 | F26: =F18*F$23*$A27 -> 1.6038803e-05
A27: =J4 -> 0.068311354 | B27: MMM | C27: =C19*C$23*$A28 -> 3.8837103e-05 | D27: =D19*D$23*$A28 -> 6.2066593e-06 | E27: =E19*E$23*$A28 -> 3.0768359e-06 | F27: =F19*F$23*$A28 -> 3.1040623e-06
A28: =K4 -> 0.027609596 | B28: SLV | C28: =C20*C$23*$A29 -> 0.00011306429 | D28: =D20*D$23*$A29 -> 1.6038803e-05 | E28: =E20*E$23*$A29 -> 3.1040623e-06 | F28: =F20*F$23*$A29 -> 0.00016123907
A29: =L4 -> 0.14042413
A32: Border Mult Cov Matrix Geometric | C32: =I11 -> 0.97139826 | D32: =J11 -> 0 | E32: =K11 -> 0 | F32: =L11 -> 0.02860174
C33: SPY | D33: A | E33: MMM | F33: SLV
B34: SPY | C34: =C17*C$32*$A35 -> 0.0018285269 | D34: =D17*D$32*$A35 -> 0 | E34: =E17*E$32*$A35 -> 0 | F34: =F17*F$32*$A35 -> 2.9293842e-05
A35: =I11 -> 0.97139826 | B35: A | C35: =C18*C$32*$A36 -> 0 | D35: =D18*D$32*$A36 -> 0 | E35: =E18*E$32*$A36 -> 0 | F35: =F18*F$32*$A36 -> 0
A36: =J11 -> 0 | B36: MMM | C36: =C19*C$32*$A37 -> 0 | D36: =D19*D$32*$A37 -> 0 | E36: =E19*E$32*$A37 -> 0 | F36: =F19*F$32*$A37 -> 0
A37: =K11 -> 0 | B37: SLV | C37: =C20*C$32*$A38 -> 2.9293842e-05 | D37: =D20*D$32*$A38 -> 0 | E37: =E20*E$32*$A38 -> 0 | F37: =F20*F$32*$A38 -> 6.6891614e-06
A38: =L11 -> 0.02860174
A41: Border Mult Cov Matrix Arithmetic Three Asset | C41: =I19 -> 0.90025659 | D41: =J19 -> 0.08974319 | E41: =K19 -> 0.010000238
C42: SPY | D42: A | E42: MMM
B43: SPY | C43: =C17*C$41*$A44 -> 0.001570505 | D43: =D17*D$41*$A44 -> 0.00020406098 | E43: =E17*E$41*$A44 -> 1.6583121e-05
A44: =I19 -> 0.90025659 | B44: A | C44: =C18*C$41*$A45 -> 0.00020406098 | D44: =D18*D$41*$A45 -> 5.7316958e-05 | E44: =E18*E$41*$A45 -> 2.9533629e-06
A45: =J19 -> 0.08974319 | B45: MMM | C45: =C19*C$41*$A46 -> 1.6583121e-05 | D45: =D19*D$41*$A46 -> 2.9533629e-06 | E45: =E19*E$41*$A46 -> 4.0364997e-07
A46: =K19 -> 0.010000238

Sheet Plotting Markowitz
B3: Asset | C3: Sd | D3: E[R] | E3: Sharpe
B4: SPY | C4: ='Markowitz II'!E3 -> 0.044020337 | D4: ='Markowitz II'!C3 -> 0.0080059016 | E4: =(D4-$C$11)/C4 -> 0.16293761
B5: A | C5: ='Markowitz II'!E4 -> 0.084360679 | D5: ='Markowitz II'!C4 -> 0.011451661 | E5: =(D5-$C$11)/C5 -> 0.12586821
B6: MMM | C6: ='Markowitz II'!E5 -> 0.06353194 | D6: ='Markowitz II'!C5 -> 0.0080216585 | E6: =(D6-$C$11)/C6 -> 0.11314506
B7: SLV | C7: ='Markowitz II'!E6 -> 0.090426014 | D7: ='Markowitz II'!C6 -> 0.0089298086 | E7: =(D7-$C$11)/C7 -> 0.089537013
B8: Optimal 4A | C8: ='Markowitz II'!J7 -> 0.044109018 | D8: ='Markowitz II'!K7 -> 0.00837146 | E8: =(D8-$C$11)/C8 -> 0.17089763
B9: Optimal 3A | C9: ='Markowitz II'!J22 -> 0.045556784 | D9: ='Markowitz II'!K22 -> 0.0083152928 | E9: =(D9-$C$11)/C9 -> 0.16423371
B11: Rf | C11: =1%/12 -> 0.00083333333
B13: SD | C13: CAL 3A | D13: CAL 4A
B14: 0 | C14: =C11 -> 0.00083333333 | D14: =C11 -> 0.00083333333
B15: 0.02 | C15: =$C$11+$E$9*B15 -> 0.0041180074 | D15: =$C$11+$E$8*B15 -> 0.004251286
B16: 0.04 | C16: =$C$11+$E$9*B16 -> 0.0074026816 | D16: =$C$11+$E$8*B16 -> 0.0076692386
B17: 0.06 | C17: =$C$11+$E$9*B17 -> 0.010687356 | D17: =$C$11+$E$8*B17 -> 0.011087191
B18: 0.08 | C18: =$C$11+$E$9*B18 -> 0.01397203 | D18: =$C$11+$E$8*B18 -> 0.014505144
B19: 0.1 | C19: =$C$11+$E$9*B19 -> 0.017256704 | D19: =$C$11+$E$8*B19 -> 0.017923097

Sheet R Verify Sheet
B3: Stock | C3: Bond | D3: Commodities | F3: w_Stock | G3: w_Bond | H3: w_Commodities
A4: E[R] | B4: 0.06 | C4: 0.04 | D4: 0.025 | F4: 0.095220839 | G4: 0.38573512 | H4: 0.51904404 | I4: =SUM(F4:H4) -> 1
A5: Standard Deviation | B5: 0.2 | C5: 0.1 | D5: 0.07
F6: Rf | G6: Er | H6: SD | I6: Sharpe
A7: Correlation | F7: =1% -> 0.01 | G7: =F4*B4+G4*C4+H4*D4 -> 0.034118756 | H7: =SQRT(SUM(B21:D23)) -> 0.055763913 | I7: =(G7-F7)/H7 -> 0.43251549
B8: Stock | C8: Bond | D8: Commodities
A9: Stock | B9: 1 | C9: 0.389 | D9: -0.05
A10: Bond | B10: 0.389 | C10: 1 | D10: -0.201
A11: Commodities | B11: -0.05 | C11: -0.201 | D11: 1
A13: Bordered Covariance
B14: Stock | C14: Bond | D14: Commodties
A15: Stock | B15: =F$17*F17*B9 -> 0.04 | C15: =$F17*G17*C9 -> 0.00778 | D15: =$F17*H17*D9 -> -0.0007
A16: Bond | B16: =F17*$F18*B10 -> 0.00778 | C16: =G17*$F18*C10 -> 0.01 | D16: =H17*$F18*D10 -> -0.001407
A17: Commodities | B17: =F17*$F19*B11 -> -0.0007 | C17: =G17*$F19*C11 -> -0.001407 | D17: =H17*$F19*D11 -> 0.0049 | F17: 0.2 | G17: 0.1 | H17: 0.07
F18: 0.1
A19: Border Multiplied Cov | F19: 0.07
B20: =F4 -> 0.095220839 | C20: =G4 -> 0.38573512 | D20: =H4 -> 0.51904404
A21: =F4 -> 0.095220839 | B21: =B$20*A21*B15 -> 0.00036268033 | C21: =C20*$A21*C15 -> 0.00028575957 | D21: =D20*$A21*D15 -> -3.4596666e-05
A22: =G4 -> 0.38573512 | B22: =B20*$A22*B16 -> 0.00028575957 | C22: =C20*$A22*C16 -> 0.0014879159 | D22: =D20*$A22*D16 -> -0.00028170042
A23: =H4 -> 0.51904404 | B23: =B$20*$A23*B17 -> -3.4596666e-05 | C23: =C$20*$A23*C17 -> -0.00028170042 | D23: =D$20*$A23*D17 -> 0.0013200929
